nlevo_shell/__init__.py
nlevo_shell/loop.py
nlevo_shell/main.py
nlevo_shell/test.py
nlevo_shell/connections/__init__.py
nlevo_shell/connections/connections.py
nlevo_shell/connections/redis.py
nlevo_shell/core/__init__.py
nlevo_shell/core/config.py
nlevo_shell/core/core_consumer.py
nlevo_shell/core/process_controller.py
nlevo_shell/core/generator/__init__.py
nlevo_shell/core/generator/message_generator.py
nlevo_shell/core/rabbitmq/__init__.py
nlevo_shell/core/rabbitmq/rabbitmq_consumer.py
nlevo_shell/core/rabbitmq/rabbitmq_producer.py
nlevo_shell/core/rabbitmq/rabbitmq_utils.py
nlevo_shell/log_service/__init__.py
nlevo_shell/log_service/device_command_handler.py
nlevo_shell/log_service/logcollector_controller.py
nlevo_shell/log_service/adb_log/__init__.py
nlevo_shell/log_service/adb_log/log_manager.py
nlevo_shell/log_service/adb_log/parse.py
nlevo_shell/util/__init__.py
nlevo_shell/util/common.py
tests/__init__.py
nlevo_shell-0.0.1.dist-info/METADATA
nlevo_shell-0.0.1.dist-info/WHEEL
nlevo_shell-0.0.1.dist-info/top_level.txt
nlevo_shell-0.0.1.dist-info/RECORD
