Metadata-Version: 2.1
Name: nlevo-shell
Version: 0.0.1
Summary: Shell module for evo.C
Author: nextlab
Author-email: jay101@nextlab.co.kr
Classifier: Programming Language :: Python :: 3
Classifier: License :: OSI Approved :: MIT License
Classifier: Operating System :: OS Independent
Requires-Python: >=3.10
Requires-Dist: numpy ==1.26.4
Requires-Dist: joblib ==1.4.2
Requires-Dist: paramiko ==3.4.1
Requires-Dist: adbutils ==2.8.0
Requires-Dist: kombu >=5.4.2
Requires-Dist: pika >=1.3.2
Requires-Dist: redis >=5.1.0
Requires-Dist: clickhouse-connect >=0.8.1
Requires-Dist: pure-python-adb ==0.3.0.dev0
Requires-Dist: retry >=0.9.2
Requires-Dist: nlevo >=0.0.14
Requires-Dist: iterators >=0.2.0
Requires-Dist: pydantic ==1.10.15
Requires-Dist: Pillow >=10.1.0
